exstruct/__init__.py
exstruct/cli/availability.py
exstruct/cli/main.py
exstruct/core/__init__.py
exstruct/core/backends/__init__.py
exstruct/core/backends/base.py
exstruct/core/backends/com_backend.py
exstruct/core/backends/openpyxl_backend.py
exstruct/core/cells.py
exstruct/core/charts.py
exstruct/core/integrate.py
exstruct/core/logging_utils.py
exstruct/core/modeling.py
exstruct/core/pipeline.py
exstruct/core/ranges.py
exstruct/core/shapes.py
exstruct/core/workbook.py
exstruct/engine.py
exstruct/errors.py
exstruct/io/__init__.py
exstruct/io/serialize.py
exstruct/mcp/__init__.py
exstruct/mcp/chunk_reader.py
exstruct/mcp/extract_runner.py
exstruct/mcp/io.py
exstruct/mcp/server.py
exstruct/mcp/tools.py
exstruct/mcp/validate_input.py
exstruct/models/__init__.py
exstruct/models/maps.py
exstruct/models/types.py
exstruct/py.typed
exstruct/render/__init__.py
exstruct-0.4.2.dist-info/WHEEL
exstruct-0.4.2.dist-info/entry_points.txt
exstruct-0.4.2.dist-info/METADATA
exstruct-0.4.2.dist-info/RECORD
