Metadata-Version: 2.3
Name: exstruct
Version: 0.4.2
Summary: Excel to structured JSON (tables, shapes, charts) for LLM/RAG pipelines
Keywords: excel,structure,data,exstruct
Author: harumiWeb
License: BSD 3-Clause License
Requires-Dist: numpy>=2.3.5
Requires-Dist: openpyxl>=3.1.5
Requires-Dist: pandas>=2.3.3
Requires-Dist: pydantic>=2.12.5
Requires-Dist: scipy>=1.16.3
Requires-Dist: xlwings>=0.33.16
Requires-Dist: pyyaml>=6.0.3 ; extra == 'all'
Requires-Dist: python-toon>=0.1.3 ; extra == 'all'
Requires-Dist: pypdfium2>=5.1.0 ; extra == 'all'
Requires-Dist: pillow>=12.0.0 ; extra == 'all'
Requires-Dist: mcp>=1.6.0,<2.0.0 ; extra == 'all'
Requires-Dist: httpx>=0.27,<1.0 ; extra == 'all'
Requires-Dist: mcp>=1.6.0,<2.0.0 ; extra == 'mcp'
Requires-Dist: httpx>=0.27,<1.0 ; extra == 'mcp'
Requires-Dist: pypdfium2>=5.1.0 ; extra == 'render'
Requires-Dist: pillow>=12.0.0 ; extra == 'render'
Requires-Dist: python-toon>=0.1.3 ; extra == 'toon'
Requires-Dist: pyyaml>=6.0.3 ; extra == 'yaml'
Requires-Python: >=3.11
Project-URL: Documentation, https://harumiweb.github.io/exstruct/
Project-URL: Homepage, https://harumiweb.github.io/exstruct/
Project-URL: Issues, https://github.com/harumiWeb/exstruct/issues
Project-URL: Repository, https://github.com/harumiWeb/exstruct
Provides-Extra: all
Provides-Extra: mcp
Provides-Extra: render
Provides-Extra: toon
Provides-Extra: yaml
